maga.py
Maga-3.0.0.dist-info/DESCRIPTION.rst
Maga-3.0.0.dist-info/METADATA
Maga-3.0.0.dist-info/RECORD
Maga-3.0.0.dist-info/WHEEL
Maga-3.0.0.dist-info/metadata.json
Maga-3.0.0.dist-info/top_level.txt
