Metadata-Version: 2.0
Name: Maga
Version: 3.0.0
Summary: A DHT crawler framework using asyncio.
Home-page: https://github.com/whtsky/maga
Author: whtsky
Author-email: whtsky@gmail.com
License: BSDv3
Keywords: dht,asyncio,crawler,bt,kad
Platform: any
Classifier: Environment :: Other Environment
Classifier: Intended Audience :: Developers
Classifier: License :: OSI Approved :: BSD License
Classifier: Operating System :: OS Independent
Classifier: Programming Language :: Python
Classifier: Programming Language :: Python :: 3.5
Classifier: Programming Language :: Python :: Implementation :: CPython
Requires-Dist: bencoder.pyx (>=1.1.1)
